tetris_study_league_tools/__init__.py
tetris_study_league_tools/__main__.py
tetris_study_league_tools/avatar.py
tetris_study_league_tools/browser.py
tetris_study_league_tools/constant.py
tetris_study_league_tools/exception.py
tetris_study_league_tools/log.py
tetris_study_league_tools/request.py
tetris_study_league_tools/retry.py
tetris_study_league_tools/api/__init__.py
tetris_study_league_tools/api/cache.py
tetris_study_league_tools/api/player.py
tetris_study_league_tools/api/typing.py
tetris_study_league_tools/api/schemas/user.py
tetris_study_league_tools/api/schemas/user_info.py
tetris_study_league_tools/api/schemas/base/__init__.py
tetris_study_league_tools/api/schemas/base/solo.py
tetris_study_league_tools/api/schemas/summaries/__init__.py
tetris_study_league_tools/api/schemas/summaries/base.py
tetris_study_league_tools/api/schemas/summaries/league.py
tetris_study_league_tools/api/schemas/summaries/solo.py
tetris_study_league_tools-0.1.0.dist-info/METADATA
tetris_study_league_tools-0.1.0.dist-info/WHEEL
tetris_study_league_tools-0.1.0.dist-info/entry_points.txt
tetris_study_league_tools-0.1.0.dist-info/RECORD
