Metadata-Version: 2.3
Name: tetris-study-league-tools
Version: 0.1.0
Summary: 一个供研究联赛使用的小工具
Requires-Python: >=3.12
Requires-Dist: aiocache>=0.12.3
Requires-Dist: httpx>=0.27.2
Requires-Dist: loguru>=0.7.2
Requires-Dist: msgspec>=0.18.6
Requires-Dist: nicegui>=2.3.0
Requires-Dist: playwright>=1.47.0
Requires-Dist: pydantic>=2.9.2
Requires-Dist: rich>=13.9.2
Requires-Dist: richuru>=0.1.1
Requires-Dist: xlsxwriter>=3.2.0
Requires-Dist: yarl>=1.14.0
